{
  "adult": false,
  "backdrop_path": "/ouN0GyE7mtIT6wyJeilaggyvgNj.jpg",
  "belongs_to_collection": null,
  "budget": 15000000,
  "genres": [
    {
      "id": 18,
      "name": "Drama"
    },
    {
      "id": 80,
      "name": "Crime"
    }
  ],
  "homepage": "https://a24films.com/films/the-bling-ring",
  "id": 96936,
  "imdb_id": "tt2132285",
  "origin_country": [
    "US"
  ],
  "original_language": "en",
  "original_title": "The Bling Ring",
  "overview": "Lured by stardom, a crew of aimless teens breaks into celebrity homes for a string of high-profile robberies and fame by appropriation.",
  "popularity": 3.0409,
  "poster_path": "/6yh55qCcdgPRJweDWM2CiEubJCL.jpg",
  "production_companies": [
    {
      "id": 70,
      "logo_path": "/ueaENQkPcy8rlr5fGZVBXKOhlBh.png",
      "name": "American Zoetrope",
      "origin_country": "US"
    },
    {
      "id": 2088,
      "logo_path": "/AoCD5EcqTAuLkxwsKAXYG2VARPP.png",
      "name": "NALA Films",
      "origin_country": "US"
    },
    {
      "id": 7981,
      "logo_path": "/6Yv1gIAuGkHS5Vis4UjnqHhCPWV.png",
      "name": "Pathé",
      "origin_country": "FR"
    }
  ],
  "production_countries": [
    {
      "iso_3166_1": "US",
      "name": "United States of America"
    },
    {
      "iso_3166_1": "FR",
      "name": "France"
    }
  ],
  "release_date": "2013-06-12",
  "revenue": 19145732,
  "runtime": 90,
  "softcore": false,
  "spoken_languages": [
    {
      "english_name": "English",
      "iso_639_1": "en",
      "name": "English"
    }
  ],
  "status": "Released",
  "tagline": "Living the dream, one heist at a time.",
  "title": "The Bling Ring",
  "video": false,
  "vote_average": 5.431,
  "vote_count": 3157,
  "external_ids": {
    "imdb_id": "tt2132285",
    "wikidata_id": "Q3077738",
    "facebook_id": null,
    "instagram_id": null,
    "twitter_id": null
  }
}