{
  "Title": "Cut Bank",
  "Year": "2014",
  "Rated": "R",
  "Released": "03 Apr 2015",
  "Runtime": "93 min",
  "Genre": "Crime, Drama, Mystery",
  "Director": "Matt Shakman",
  "Writer": "Roberto Patino",
  "Actors": "Michael Stuhlbarg, Bruce Dern, John Malkovich",
  "Plot": "A murder caught on camera pulls a young man into a high-stakes game of cat-and-mouse.",
  "Language": "English",
  "Country": "United States",
  "Awards": "2 wins & 3 nominations total",
  "Poster": "https://m.media-amazon.com/images/M/MV5BMzk2NDg2MDEwNV5BMl5BanBnXkFtZTgwNDk2Mjk0NDE@._V1_SX300.jpg",
  "Ratings": [
    {
      "Source": "Internet Movie Database",
      "Value": "6.1/10"
    },
    {
      "Source": "Rotten Tomatoes",
      "Value": "39%"
    },
    {
      "Source": "Metacritic",
      "Value": "44/100"
    }
  ],
  "Metascore": "44",
  "imdbRating": "6.1",
  "imdbVotes": "14,352",
  "imdbID": "tt1661820",
  "Type": "movie",
  "DVD": "N/A",
  "BoxOffice": "N/A",
  "Production": "N/A",
  "Website": "N/A",
  "Response": "True"
}