{
  "Title": "The Killing of a Sacred Deer",
  "Year": "2017",
  "Rated": "R",
  "Released": "03 Nov 2017",
  "Runtime": "121 min",
  "Genre": "Drama, Horror, Mystery",
  "Director": "Yorgos Lanthimos",
  "Writer": "Yorgos Lanthimos, Efthimis Filippou",
  "Actors": "Barry G. Bernson, Herb Caillouet, Bill Camp",
  "Plot": "A devious teen starts to insinuate himself into the life of a renowned surgeon and his family.",
  "Language": "English, French",
  "Country": "Ireland, United Kingdom, United States",
  "Awards": "7 wins & 53 nominations total",
  "Poster": "https://m.media-amazon.com/images/M/MV5BMjU4NDcwOTA2NF5BMl5BanBnXkFtZTgwMjE2OTg4MzI@._V1_SX300.jpg",
  "Ratings": [
    {
      "Source": "Internet Movie Database",
      "Value": "7.0/10"
    },
    {
      "Source": "Rotten Tomatoes",
      "Value": "79%"
    },
    {
      "Source": "Metacritic",
      "Value": "73/100"
    }
  ],
  "Metascore": "73",
  "imdbRating": "7.0",
  "imdbVotes": "212,973",
  "imdbID": "tt5715874",
  "Type": "movie",
  "DVD": "N/A",
  "BoxOffice": "$2,291,901",
  "Production": "N/A",
  "Website": "N/A",
  "Response": "True"
}